dnsbl_check/__init__.py
dnsbl_check/__main__.py
dnsbl_check/checker.py
dnsbl_check/config.py
dnsbl_check/provider.py
dnsbl_check/provider_config.py
dnsbl_check/result.py
dnsbl_check/test_1_checker.py
dnsbl_check/test_2_providers.py
dnsbl_check/test_3_real.py
dnsbl_check/test_4_cli.py
dnsbl_check-2.0.2.dist-info/licenses/LICENSE
dnsbl_check-2.0.2.dist-info/METADATA
dnsbl_check-2.0.2.dist-info/WHEEL
dnsbl_check-2.0.2.dist-info/entry_points.txt
dnsbl_check-2.0.2.dist-info/top_level.txt
dnsbl_check-2.0.2.dist-info/RECORD
