Metadata-Version: 2.4
Name: dnsbl-check
Version: 2.0.2
Summary: OXL DNSBL Checker
Author-email: Rath Pascal <contact@oxl.at>
Project-URL: Homepage, https://www.oxl.at
Project-URL: Documentation, https://github.com/O-X-L/dnsbl-checker
Project-URL: Repository, https://github.com/O-X-L/dnsbl-checker.git
Project-URL: Issues, https://github.com/O-X-L/dnsbl-checker/issues
Keywords: dnsbl,blocklists
Classifier: Programming Language :: Python :: 3
Classifier: License :: OSI Approved :: MIT License
Requires-Python: >=3.10
License-File: LICENSE
Requires-Dist: idna
Requires-Dist: aiodns
Dynamic: license-file
